Metadata-Version: 2.1
Name: odoo12-addon-l10n-it-corrispettivi-sale
Version: 12.0.1.0.3
Summary: Modulo per integrare le ricevute in Odoo con gli ordini di vendita.
Home-page: https://github.com/OCA/l10n-italy/tree/12.0/l10n_it_corrispettivi_sale
Author: Agile Business Group, Odoo Community Association (OCA)
Author-email: support@odoo-community.org
License: AGPL-3
Platform: UNKNOWN
Classifier: Programming Language :: Python
Classifier: Framework :: Odoo
Classifier: License :: OSI Approved :: GNU Affero General Public License v3
Requires-Python: >=3.5
Requires-Dist: odoo12-addon-l10n-it-corrispettivi
Requires-Dist: odoo (<12.1dev,>=12.0a)
